toymm/__init__.py
toymm/py.typed
toymm-0.0.1a0.dist-info/licenses/LICENSE
toymm-0.0.1a0.dist-info/METADATA
toymm-0.0.1a0.dist-info/WHEEL
toymm-0.0.1a0.dist-info/top_level.txt
toymm-0.0.1a0.dist-info/zip-safe
toymm-0.0.1a0.dist-info/RECORD
