Metadata-Version: 2.4
Name: toymm
Version: 0.0.1a0
Summary: Multimodal from scratch
Author-email: Xiangzhuang Shen <datahonor@gmail.com>
License-Expression: MIT
Project-URL: Homepage, https://shenxiangzhuang.github.io/toymm
Project-URL: Bug Tracker, https://shenxiangzhuang.github.io/toymm/issues
Project-URL: Documentation, https://shenxiangzhuang.github.io/toymm
Project-URL: Source Code, https://github.com/shenxiangzhuang/toymm
Project-URL: Release Notes, https://shenxiangzhuang.github.io/toymm/changelog/
Classifier: Development Status :: 3 - Alpha
Classifier: Intended Audience :: Science/Research
Classifier: Intended Audience :: Developers
Classifier: Operating System :: OS Independent
Classifier: Programming Language :: Python :: 3.12
Classifier: Programming Language :: Python :: 3.13
Requires-Python: >=3.12
License-File: LICENSE
Provides-Extra: dev
Requires-Dist: pre-commit; extra == "dev"
Requires-Dist: ipython; extra == "dev"
Requires-Dist: mypy; extra == "dev"
Requires-Dist: ruff; extra == "dev"
Requires-Dist: pytest; extra == "dev"
Requires-Dist: pytest-cov; extra == "dev"
Requires-Dist: pytest-sugar; extra == "dev"
Requires-Dist: hypothesis; extra == "dev"
Provides-Extra: docs
Requires-Dist: mkdocs; extra == "docs"
Requires-Dist: mkdocs-material; extra == "docs"
Requires-Dist: mkdocs-material-extensions; extra == "docs"
Requires-Dist: mkdocstrings; extra == "docs"
Requires-Dist: mkdocs-bibtex; extra == "docs"
Requires-Dist: mkdocstrings-python; extra == "docs"
Requires-Dist: mkdocs-autorefs; extra == "docs"
Requires-Dist: mkdocs-git-committers-plugin-2; extra == "docs"
Requires-Dist: mkdocs-git-revision-date-localized-plugin; extra == "docs"
Dynamic: license-file
